banner_monk/__init__.py
banner_monk/banner_monk.py
banner_monk-0.3.1.dist-info/METADATA
banner_monk-0.3.1.dist-info/WHEEL
banner_monk-0.3.1.dist-info/entry_points.txt
banner_monk-0.3.1.dist-info/top_level.txt
banner_monk-0.3.1.dist-info/RECORD
