Metadata-Version: 2.1
Name: banner_monk
Version: 0.3.1
Summary: Printing banner out
Author-email: thephunkmonk <andrewchoi1218@gmail.com>
License: MIT
Project-URL: Homepage, https://github.com/thephunkmonk/banner_monk
Project-URL: Issues, https://github.com/thephunkmonk/banner_monk/issues
Requires-Python: >=3.9
Requires-Dist: pyfiglet >=1.0.2
